{
  "timestamp": "2025-10-28T09:30:00-04:00",
  "timestamp_end": "2025-10-28T11:00:00-04:00",
  "state": "incomplete",
  "progress": 0,
  "title": "Dienstag, 28.10.2025 09:30",
  "symbols": [
    "NVDA",
    "MSFT",
    "AAPL",
    "GOOG",
    "AMZN",
    "META",
    "AVGO",
    "TSLA",
    "BRK B",
    "ORCL",
    "JPM",
    "WMT",
    "LLY",
    "V",
    "NFLX",
    "MA",
    "XOM",
    "JNJ",
    "PLTR",
    "COST",
    "ABBV",
    "HD",
    "BAC",
    "AMD",
    "PG",
    "UNH",
    "GE",
    "CVX",
    "KO",
    "CSCO",
    "IBM",
    "TMUS",
    "WFC",
    "PM",
    "MS",
    "GS",
    "CRM",
    "CAT",
    "ABT",
    "AXP",
    "MU",
    "MCD",
    "LIN",
    "MRK",
    "RTX",
    "PEP",
    "APP",
    "DIS",
    "TMO",
    "UBER",
    "BX",
    "NOW",
    "BLK",
    "ANET",
    "T"
  ],
  "symbols_signal": [],
  "symbols_long": [],
  "symbols_short": []
}